{
  "label": "india",
  "value": null,
  "children": [
    {
      "label": "meta",
      "value": null,
      "children": [
        {
          "label": "country_name",
          "value": "India",
          "children": []
        },
        {
          "label": "retrieved_at",
          "value": "2026-03-13T11:37:06+00:00",
          "children": []
        },
        {
          "label": "slug",
          "value": "india",
          "children": []
        },
        {
          "label": "source",
          "value": "wikipedia-infobox",
          "children": []
        },
        {
          "label": "wikipedia_url",
          "value": "https://en.wikipedia.org/wiki/India",
          "children": []
        }
      ]
    },
    {
      "label": "fields",
      "value": null,
      "children": [
        {
          "label": "area",
          "value": null,
          "children": [
            {
              "label": "total_km2",
              "value": "3287263",
              "children": []
            },
            {
              "label": "water_percent",
              "value": "9.6",
              "children": []
            }
          ]
        },
        {
          "label": "calling_code",
          "value": "91",
          "children": []
        },
        {
          "label": "capital",
          "value": "New Delhi",
          "children": []
        },
        {
          "label": "country_name",
          "value": "India",
          "children": []
        },
        {
          "label": "currency",
          "value": null,
          "children": [
            {
              "label": "name",
              "value": "Indian rupee",
              "children": []
            }
          ]
        },
        {
          "label": "development",
          "value": null,
          "children": [
            {
              "label": "gini",
              "value": null,
              "children": [
                {
                  "label": "value",
                  "value": "25.5",
                  "children": []
                },
                {
                  "label": "year",
                  "value": "2022",
                  "children": []
                }
              ]
            },
            {
              "label": "hdi",
              "value": null,
              "children": [
                {
                  "label": "rank",
                  "value": "130",
                  "children": []
                },
                {
                  "label": "value",
                  "value": "0.685",
                  "children": []
                },
                {
                  "label": "year",
                  "value": "2023",
                  "children": []
                }
              ]
            }
          ]
        },
        {
          "label": "economy",
          "value": null,
          "children": [
            {
              "label": "gdp_nominal_per_capita",
              "value": "$2,878",
              "children": []
            },
            {
              "label": "gdp_nominal_total",
              "value": "$4.187 trillion",
              "children": []
            },
            {
              "label": "gdp_nominal_year",
              "value": "2025",
              "children": []
            },
            {
              "label": "gdp_ppp_per_capita",
              "value": "$12,132",
              "children": []
            },
            {
              "label": "gdp_ppp_total",
              "value": "$17.647 trillion",
              "children": []
            },
            {
              "label": "gdp_ppp_year",
              "value": "2025",
              "children": []
            }
          ]
        },
        {
          "label": "government",
          "value": null,
          "children": [
            {
              "label": "head_of_government",
              "value": "Narendra Modi",
              "children": []
            },
            {
              "label": "head_of_state",
              "value": "Droupadi Murmu",
              "children": []
            },
            {
              "label": "type",
              "value": "Federal parliamentary republic",
              "children": []
            }
          ]
        },
        {
          "label": "internet_tld",
          "value": null,
          "children": [
            {
              "label": "internet_tld_item",
              "value": ".in",
              "children": []
            },
            {
              "label": "internet_tld_item",
              "value": "(",
              "children": []
            },
            {
              "label": "internet_tld_item",
              "value": "others",
              "children": []
            },
            {
              "label": "internet_tld_item",
              "value": ")",
              "children": []
            }
          ]
        },
        {
          "label": "iso_3166_code",
          "value": "IN",
          "children": []
        },
        {
          "label": "languages",
          "value": null,
          "children": [
            {
              "label": "official",
              "value": null,
              "children": [
                {
                  "label": "official_item",
                  "value": "Hindi English",
                  "children": []
                }
              ]
            }
          ]
        },
        {
          "label": "largest_city",
          "value": "New Delhi",
          "children": []
        },
        {
          "label": "legislature",
          "value": "Parliament",
          "children": []
        },
        {
          "label": "population",
          "value": null,
          "children": [
            {
              "label": "density_per_km2",
              "value": "433.4",
              "children": []
            },
            {
              "label": "rank",
              "value": "1",
              "children": []
            },
            {
              "label": "total",
              "value": "1428627663",
              "children": []
            },
            {
              "label": "year",
              "value": "2023",
              "children": []
            }
          ]
        },
        {
          "label": "time_zone",
          "value": null,
          "children": [
            {
              "label": "standard",
              "value": "UTC+05:30",
              "children": []
            }
          ]
        }
      ]
    }
  ]
}